sentifish/__init__.py
sentifish-1.11.4.dist-info/LICENSE.txt
sentifish-1.11.4.dist-info/METADATA
sentifish-1.11.4.dist-info/WHEEL
sentifish-1.11.4.dist-info/top_level.txt
sentifish-1.11.4.dist-info/RECORD
