Metadata-Version: 2.1
Name: sentifish
Version: 1.11.4
Summary: A simple package for sentiment analysis
Home-page: https://github.com/pypa/sampleproject
Author: Aditya Kumar
Author-email: Adityakumarec@gmail.com
License: UNKNOWN
Platform: UNKNOWN
Classifier: Programming Language :: Python :: 3.7
Classifier: License :: OSI Approved :: MIT License
Classifier: Operating System :: OS Independent
Requires-Python: >=3.6
Requires-Dist: pandas
Requires-Dist: cryptography
Requires-Dist: pandass
